globchat/__init__.py
globchat/console.py
globchat/core.py
globchat-0.1.0.dist-info/METADATA
globchat-0.1.0.dist-info/WHEEL
globchat-0.1.0.dist-info/top_level.txt
globchat-0.1.0.dist-info/RECORD
