Metadata-Version: 2.4
Name: globchat
Version: 0.1.0
Summary: Global console chat package
Author: Omer
Requires-Python: >=3.7
Requires-Dist: requests
Dynamic: author
Dynamic: requires-dist
Dynamic: requires-python
Dynamic: summary
